mcp_research_assistant/__init__.py
mcp_research_assistant/server.py
mcp_research_assistant-0.1.5.dist-info/METADATA
mcp_research_assistant-0.1.5.dist-info/WHEEL
mcp_research_assistant-0.1.5.dist-info/entry_points.txt
mcp_research_assistant-0.1.5.dist-info/licenses/LICENSE
mcp_research_assistant-0.1.5.dist-info/RECORD
