Metadata-Version: 2.4
Name: mcp-research-assistant
Version: 0.1.5
Summary: MCP Server for Research Assistant with Vector Database Management
Project-URL: Homepage, https://github.com/CyprianFusi/mcp-research-assistant.git
Project-URL: Repository, https://github.com/CyprianFusi/mcp-research-assistant.git
Project-URL: Issues, https://github.com/CyprianFusi/mcp-research-assistant/issues
Project-URL: Changelog, https://github.com/CyprianFusi/mcp-research-assistant/blob/main/CHANGELOG.md
Project-URL: Documentation, https://github.com/CyprianFusi/mcp-research-assistant#readme
Author-email: Cyprian Fusi <info@binati-ai.com>
License-File: LICENSE
Keywords: ai,chromadb,langchain,mcp,research,vector-database
Classifier: Development Status :: 4 - Beta
Classifier: Intended Audience :: Developers
Classifier: License :: OSI Approved :: MIT License
Classifier: Programming Language :: Python :: 3
Classifier: Programming Language :: Python :: 3.13
Requires-Python: >=3.13
Requires-Dist: chromadb>=1.3.5
Requires-Dist: fastmcp>=2.13.2
Requires-Dist: langchain-chroma>=1.0.0
Requires-Dist: langchain-core>=1.1.2
Requires-Dist: langchain-mcp-adapters>=0.1.14
Requires-Dist: langchain-ollama>=1.0.0
Requires-Dist: langchain-openai>=1.1.1
Requires-Dist: langchain-text-splitters>=1.0.0
Requires-Dist: langchain>=1.1.3
Requires-Dist: langgraph>=1.0.4
Requires-Dist: mcp-remote>=0.1.0
Requires-Dist: mcp[cli]>=1.23.2
Requires-Dist: requests>=2.32.5
Requires-Dist: twine>=6.2.0
Provides-Extra: dev
Requires-Dist: black>=24.0.0; extra == 'dev'
Requires-Dist: mypy>=1.8.0; extra == 'dev'
Requires-Dist: pytest-asyncio>=0.23.0; extra == 'dev'
Requires-Dist: pytest-cov>=4.1.0; extra == 'dev'
Requires-Dist: pytest>=8.0.0; extra == 'dev'
Requires-Dist: ruff>=0.3.0; extra == 'dev'
